[{"content":"《Can\u0026rsquo;t hurt me》（中文：我，刀槍不入）是至今影響我心志、毅力、韌性最深的一本書。\n這本書深刻影響我的地方太多，這篇文章想講其中一個：滿手爛牌起手的壯闊人生\n人生遇到缺憾時，以前心志弱小的我，總不免怨天尤人。\n二十幾歲很想去矽谷闖蕩，但是沒有美國身份，想在美國長期居留諸多困難，就想：「啊，我出生在美國，有美國國籍就好了。」\n三十幾歲買房子，看著嚮往卻買不起的房子，就想：「啊，我阿公有留一筆鉅額遺產給我就好了。」\n《我，刀槍不入》的作者大衛哥金斯從小在貧窮、家暴是日常的環境中長大，擺脫家暴環境開始正常上學時，程度遠遠不及同齡學童。\n他拿著這手比絕大多數的人都爛的起手牌，力抗萬難，最後成為美國海豹突擊隊隊員、極限運動員、引體向上金氏世界紀錄保持人。\n關於自己的人生被發了一手爛牌，哥金斯在書中比喻：「這就像背著 50 磅的軍用背包跑步。」\n人生是跨過的障礙的總和。背著 50 磅的背包前進會比沒負重的人辛苦，但不代表過程會比較不精采。\n負重訓練，會讓你變成更強更卓越的鐵人。\n負重訓練的鐵人，會在拋開負重的那一刻，跑得更快更遠。\n「原生環境發給你的起手牌，不會影響人生的精彩程度」這個想法，給我很大的啟發。\n「確實，我沒辦法靠祖上餘蔭輕鬆買下嚮往的房子，但是設定賺錢目標、用自己賺的錢把嚮往的房子買下來，豈不是更酷更有趣，還可以讓自己變更強？」我現在如是想。\n","permalink":"https://read.ninja/blog/race-with-ruck/","summary":"人生是跨過的障礙的總和。背著 50 磅的背包前進會比沒負重的人辛苦，但不代表過程會比較不精采。","title":"滿手爛牌起手的壯闊人生"},{"content":"這週在 Barking Up the Wrong Tree 這本書上，讀到一個調查，是關於臨終前的人最懊悔的事。\n第五名：我希望我讓自己更開心\n很多人直到臨終前，才意識到「開心」是個選擇。後悔做這件事的人，害怕改變、害怕做決定，不敢做讓自己更開心的抉擇。\n第四名：我希望能與朋友保持聯絡\n每個人各有際遇，隨著時間推進，曾經的好友漸漸不再有交集是很正常的生命歷程。很多人在臨終前，後悔自己花太多時間在自己的生活，而沒有保持美好的友誼。\n第三名：我希望我勇敢表達我的感受\n很多人為了避免衝突，壓抑自己的各種情緒。最後活出中庸但「不是自己」的人生。\n第二名：我希望我沒有那麼認真工作\n這項調查中所有受訪的男性，全部表達了這項後悔。 （太驚人了，全部！！）\n這些男性，認為自己花太多時間在工作，花太少時間和家人相處。\n當然也有部分女性提到這個後悔。\n第一名：我希望我有勇氣活我自己想要的生活，而不是別人對我期望的生活\n這是最常見的懊悔。\n其中，多數的受訪者表示，他們回顧自己曾經擁有的各種夢想時，有一半的夢想連嘗試的勇氣都沒有。他們在「或許我當初做了這個決定，我的生命會不一樣」的懊悔中走向生命的終點。\n延伸我在另一本書《那瓦爾寶典》中讀到的，「如何不讓自己的人生後悔」的一個建議：想想你希望自己的墓誌銘上被寫什麼？\n我這週思考了這個，並慎重地在筆記本上寫下我自己的答案。\n","permalink":"https://read.ninja/blog/top-5-regrets/","summary":"第一名：我希望我有勇氣活我自己想要的生活，而不是別人對我期望的生活","title":"人生最懊悔的五件事"}]